MySDK/OCRProcessor.py
MySDK/__init__.py
HQRapidOcr-0.1.dist-info/LICENSE
HQRapidOcr-0.1.dist-info/METADATA
HQRapidOcr-0.1.dist-info/WHEEL
HQRapidOcr-0.1.dist-info/top_level.txt
HQRapidOcr-0.1.dist-info/RECORD
